XKT/__init__.py
XKT/meta.py
XKT/DKT/DKT.py
XKT/DKT/__init__.py
XKT/DKT/etl.py
XKT/DKVMN/DKVMN.py
XKT/DKVMN/__init__.py
XKT/DKVMN/etl.py
XKT/DKVMN/net.py
XKT/GKT/MGKT.py
XKT/GKT/__init__.py
XKT/GKT/etl.py
XKT/GKT/net.py
XKT/SKT/MSKT.py
XKT/SKT/__init__.py
XKT/SKT/etl.py
XKT/SKT/net.py
XKT/SKT/utils.py
XKT/utils/__init__.py
XKT/utils/etl.py
XKT/utils/loss.py
XKT/utils/tests.py
XKT/utils/nn/__init__.py
XKT/utils/nn/rnn.py
tests/__init__.py
tests/dkt/__init__.py
tests/dkt/conftest.py
tests/dkt/test_dkt.py
tests/dkvmn/__init__.py
tests/dkvmn/conftest.py
tests/dkvmn/test_dkvmn.py
tests/gkt/__init__.py
tests/gkt/conftest.py
tests/gkt/test_mgkt.py
tests/skt/__init__.py
tests/skt/conftest.py
tests/skt/test_mskt.py
XKT-0.0.2.dist-info/LICENSE
XKT-0.0.2.dist-info/METADATA
XKT-0.0.2.dist-info/WHEEL
XKT-0.0.2.dist-info/top_level.txt
XKT-0.0.2.dist-info/RECORD
